ansys/geometry/core/__init__.py
ansys/geometry/core/errors.py
ansys/geometry/core/logger.py
ansys/geometry/core/modeler.py
ansys/geometry/core/py.typed
ansys/geometry/core/typing.py
ansys/geometry/core/_grpc/_version.py
ansys/geometry/core/_grpc/_services/_service.py
ansys/geometry/core/_grpc/_services/base/admin.py
ansys/geometry/core/_grpc/_services/base/assembly_condition.py
ansys/geometry/core/_grpc/_services/base/beams.py
ansys/geometry/core/_grpc/_services/base/bodies.py
ansys/geometry/core/_grpc/_services/base/commands.py
ansys/geometry/core/_grpc/_services/base/commands_script.py
ansys/geometry/core/_grpc/_services/base/components.py
ansys/geometry/core/_grpc/_services/base/conversions.py
ansys/geometry/core/_grpc/_services/base/coordinate_systems.py
ansys/geometry/core/_grpc/_services/base/curves.py
ansys/geometry/core/_grpc/_services/base/designs.py
ansys/geometry/core/_grpc/_services/base/driving_dimensions.py
ansys/geometry/core/_grpc/_services/base/edges.py
ansys/geometry/core/_grpc/_services/base/faces.py
ansys/geometry/core/_grpc/_services/base/materials.py
ansys/geometry/core/_grpc/_services/base/measurement_tools.py
ansys/geometry/core/_grpc/_services/base/model_tools.py
ansys/geometry/core/_grpc/_services/base/named_selection.py
ansys/geometry/core/_grpc/_services/base/parts.py
ansys/geometry/core/_grpc/_services/base/patterns.py
ansys/geometry/core/_grpc/_services/base/points.py
ansys/geometry/core/_grpc/_services/base/prepare_tools.py
ansys/geometry/core/_grpc/_services/base/repair_tools.py
ansys/geometry/core/_grpc/_services/base/unsupported.py
ansys/geometry/core/_grpc/_services/v0/admin.py
ansys/geometry/core/_grpc/_services/v0/assembly_condition.py
ansys/geometry/core/_grpc/_services/v0/beams.py
ansys/geometry/core/_grpc/_services/v0/bodies.py
ansys/geometry/core/_grpc/_services/v0/commands.py
ansys/geometry/core/_grpc/_services/v0/commands_script.py
ansys/geometry/core/_grpc/_services/v0/components.py
ansys_geometry_core-0.14.2.dist-info/licenses/LICENSE
ansys_geometry_core-0.14.2.dist-info/WHEEL
ansys_geometry_core-0.14.2.dist-info/METADATA
ansys_geometry_core-0.14.2.dist-info/RECORD
