Metadata-Version: 2.4
Name: ansys-geometry-core
Version: 0.14.2
Summary: A python wrapper for Ansys Geometry service
Author-email: "ANSYS, Inc." <pyansys.core@ansys.com>
Maintainer-email: "ANSYS, Inc." <pyansys.core@ansys.com>
Requires-Python: >=3.10,<4
License-Expression: MIT
Classifier: Development Status :: 4 - Beta
Classifier: Intended Audience :: Science/Research
Classifier: Operating System :: OS Independent
Classifier: Programming Language :: Python :: 3 :: Only
Classifier: Programming Language :: Python :: 3.10
Classifier: Programming Language :: Python :: 3.11
Classifier: Programming Language :: Python :: 3.12
Classifier: Programming Language :: Python :: 3.13
Classifier: Programming Language :: Python :: 3.14
Classifier: Topic :: Scientific/Engineering :: Information Analysis
License-File: LICENSE
Requires-Dist: ansys-api-discovery==1.0.20
Requires-Dist: ansys-tools-common>=0.3,<1
Requires-Dist: beartype>=0.11.0,<0.23
Requires-Dist: geomdl>=5,<6
Requires-Dist: grpcio>=1.35.0,<2
Requires-Dist: grpcio-health-checking>=1.45.0,<2
Requires-Dist: matplotlib>=3,<4
Requires-Dist: numpy>=1.20.3,<3
Requires-Dist: pint>=0.18,<1
Requires-Dist: protobuf>=3.20.2,<7
Requires-Dist: requests>=2,<3
Requires-Dist: scipy>=1.7.3,<2
Requires-Dist: semver>=3,<4
Requires-Dist: six>=1.16.0,<2
Requires-Dist: ansys-platform-instancemanagement>=1.0.3,<2 ; extra == "all"
Requires-Dist: ansys-tools-visualization-interface>=0.2.6 ; extra == "all"
Requires-Dist: docker>=6.0.1,<8 ; extra == "all"
Requires-Dist: pygltflib>=1.16,<2 ; extra == "all"
Requires-Dist: pyvista[jupyter]>=0.38.1,<1 ; extra == "all"
Requires-Dist: vtk>=9,<10 ; extra == "all"
Requires-Dist: ansys-tools-visualization-interface>=0.2.6 ; extra == "graphics"
Requires-Dist: pygltflib>=1.16,<2 ; extra == "graphics"
Requires-Dist: pyvista[jupyter]>=0.38.1,<1 ; extra == "graphics"
Requires-Dist: vtk>=9,<10 ; extra == "graphics"
Project-URL: Changelog, https://github.com/ansys/pyansys-geometry/blob/main/doc/source/changelog.rst
Project-URL: Discussions, https://github.com/ansys/pyansys-geometry/discussions
Project-URL: Documentation, https://geometry.docs.pyansys.com
Project-URL: Issues, https://github.com/ansys/pyansys-geometry/issues
Project-URL: Releases, https://github.com/ansys/pyansys-geometry/releases
Project-URL: Source, https://github.com/ansys/pyansys-geometry
Provides-Extra: all
Provides-Extra: graphics
